Workbook

Sheet Assumptions
A1: WearWise Revenue Model — Assumptions (edit blue cells)
A3: GROWTH
A4: Starting MAU (Month 1) | B4: 5000 | C4: Beta launch base; edit to actual
A5: MoM MAU growth — Year 1 | B5: 0.2 | C5: Aggressive but achievable with viral sharing
A6: MoM MAU growth — Year 2 | B6: 0.12
A7: MoM MAU growth — Year 3 | B7: 0.08
A9: SUBSCRIPTIONS
A10: Plus conversion (% of MAU) | B10: 0.03 | C10: Industry: 2-5% freemium conversion in India
A11: Plus price (₹/month) | B11: 99
A12: Pro conversion (% of MAU) | B12: 0.01
A13: Pro price (₹/month) | B13: 199
A15: OCCASION PACKS (one-time)
A16: Pack buyers (% of MAU per month) | B16: 0.025 | C16: Wedding/travel/festive packs
A17: Average pack price (₹) | B17: 129
A19: AFFILIATE SHOPPING
A20: MAU clicking shop links per month | B20: 0.15 | C20: Gap-finder recommendations
A21: Click-to-purchase conversion | B21: 0.08
A22: Average order value (₹) | B22: 1600 | C22: Myntra/Ajio/Nykaa typical
A23: Commission rate | B23: 0.07 | C23: Fashion affiliate: 5-10%
A25: STYLIST MARKETPLACE (from Year 2)
A26: Consults (% of MAU per month) | B26: 0.003
A27: Consult price (₹) | B27: 499
A28: WearWise take rate | B28: 0.3
A30: VALUATION
A31: ARR multiple (Indian consumer subs) | B31: 7 | C31: Consumer app range: 6-10x ARR
A32: Target valuation (₹) | B32: 1000000000 | C32: ₹100 Crore
A34: REVENUE PER MAU PER MONTH (calculated)
A35: Subscriptions | B35: =B10*B11+B12*B13 -> 4.96
A36: Occasion packs | B36: =B16*B17 -> 3.225
A37: Affiliate | B37: =B20*B21*B22*B23 -> 1.344
A38: Stylist marketplace | B38: =B26*B27*B28 -> 0.4491
A39: Total (excl. stylist) | B39: =SUM(B35:B37) -> 9.529
A40: Total (incl. stylist) | B40: =SUM(B35:B38) -> 9.9781

Sheet Year 1 Monthly
A1: Year 1 — Monthly Projection
B2: M1 | C2: M2 | D2: M3 | E2: M4 | F2: M5 | G2: M6 | H2: M7 | I2: M8 | J2: M9 | K2: M10 | L2: M11 | M2: M12
A3: MAU | B3: =Assumptions!B4 -> 5000 | C3: =B3*(1+Assumptions!$B$5) -> 6000 | D3: =C3*(1+Assumptions!$B$5) -> 7200 | E3: =D3*(1+Assumptions!$B$5) -> 8640 | F3: =E3*(1+Assumptions!$B$5) -> 10368 | G3: =F3*(1+Assumptions!$B$5) -> 12441.6 | H3: =G3*(1+Assumptions!$B$5) -> 14929.92 | I3: =H3*(1+Assumptions!$B$5) -> 17915.904 | J3: =I3*(1+Assumptions!$B$5) -> 21499.085 | ... M3: =L3*(1+Assumptions!$B$5) -> 37150.419
A4: Plus subscribers | B4: =B3*Assumptions!$B$10 -> 150 | C4: =C3*Assumptions!$B$10 -> 180 | D4: =D3*Assumptions!$B$10 -> 216 | E4: =E3*Assumptions!$B$10 -> 259.2 | F4: =F3*Assumptions!$B$10 -> 311.04 | G4: =G3*Assumptions!$B$10 -> 373.248 | H4: =H3*Assumptions!$B$10 -> 447.8976 | I4: =I3*Assumptions!$B$10 -> 537.47712 | ... M4: =M3*Assumptions!$B$10 -> 1114.5126
A5: Pro subscribers | B5: =B3*Assumptions!$B$12 -> 50 | C5: =C3*Assumptions!$B$12 -> 60 | D5: =D3*Assumptions!$B$12 -> 72 | E5: =E3*Assumptions!$B$12 -> 86.4 | F5: =F3*Assumptions!$B$12 -> 103.68 | G5: =G3*Assumptions!$B$12 -> 124.416 | H5: =H3*Assumptions!$B$12 -> 149.2992 | I5: =I3*Assumptions!$B$12 -> 179.15904 | ... M5: =M3*Assumptions!$B$12 -> 371.50419
A6: Subscription revenue | B6: =B4*Assumptions!$B$11+B5*Assumptions!$B$13 -> 24800 | C6: =C4*Assumptions!$B$11+C5*Assumptions!$B$13 -> 29760 | D6: =D4*Assumptions!$B$11+D5*Assumptions!$B$13 -> 35712 | E6: =E4*Assumptions!$B$11+E5*Assumptions!$B$13 -> 42854.4 | F6: =F4*Assumptions!$B$11+F5*Assumptions!$B$13 -> 51425.28 | G6: =G4*Assumptions!$B$11+G5*Assumptions!$B$13 -> 61710.336 | H6: =H4*Assumptions!$B$11+H5*Assumptions!$B$13 -> 74052.403 | I6: =I4*Assumptions!$B$11+I5*Assumptions!$B$13 -> 88862.884 | ... M6: =M4*Assumptions!$B$11+M5*Assumptions!$B$13 -> 184266.08
A7: Occasion pack revenue | B7: =B3*Assumptions!$B$16*Assumptions!$B$17 -> 16125 | C7: =C3*Assumptions!$B$16*Assumptions!$B$17 -> 19350 | D7: =D3*Assumptions!$B$16*Assumptions!$B$17 -> 23220 | E7: =E3*Assumptions!$B$16*Assumptions!$B$17 -> 27864 | F7: =F3*Assumptions!$B$16*Assumptions!$B$17 -> 33436.8 | G7: =G3*Assumptions!$B$16*Assumptions!$B$17 -> 40124.16 | H7: =H3*Assumptions!$B$16*Assumptions!$B$17 -> 48148.992 | I7: =I3*Assumptions!$B$16*Assumptions!$B$17 -> 57778.79 | ... M7: =M3*Assumptions!$B$16*Assumptions!$B$17 -> 119810.1
A8: Affiliate revenue | B8: =B3*Assumptions!$B$20*Assumptions!$B$21*Assumptions!$B$22*Assumptions!$B$23 -> 6720 | C8: =C3*Assumptions!$B$20*Assumptions!$B$21*Assumptions!$B$22*Assumptions!$B$23 -> 8064 | D8: =D3*Assumptions!$B$20*Assumptions!$B$21*Assumptions!$B$22*Assumptions!$B$23 -> 9676.8 | E8: =E3*Assumptions!$B$20*Assumptions!$B$21*Assumptions!$B$22*Assumptions!$B$23 -> 11612.16 | F8: =F3*Assumptions!$B$20*Assumptions!$B$21*Assumptions!$B$22*Assumptions!$B$23 -> 13934.592 | G8: =G3*Assumptions!$B$20*Assumptions!$B$21*Assumptions!$B$22*Assumptions!$B$23 -> 16721.51 | H8: =H3*Assumptions!$B$20*Assumptions!$B$21*Assumptions!$B$22*Assumptions!$B$23 -> 20065.812 | I8: =I3*Assumptions!$B$20*Assumptions!$B$21*Assumptions!$B$22*Assumptions!$B$23 -> 24078.975 | ... M8: =M3*Assumptions!$B$20*Assumptions!$B$21*Assumptions!$B$22*Assumptions!$B$23 -> 49930.163
A9: Total monthly revenue | B9: =SUM(B6:B8) -> 47645 | C9: =SUM(C6:C8) -> 57174 | D9: =SUM(D6:D8) -> 68608.8 | E9: =SUM(E6:E8) -> 82330.56 | F9: =SUM(F6:F8) -> 98796.672 | G9: =SUM(G6:G8) -> 118556.01 | H9: =SUM(H6:H8) -> 142267.21 | I9: =SUM(I6:I8) -> 170720.65 | ... M9: =SUM(M6:M8) -> 354006.34
A10: Cumulative revenue | B10: =B9 -> 47645 | C10: =B10+C9 -> 104819 | D10: =C10+D9 -> 173427.8 | E10: =D10+E9 -> 255758.36 | F10: =E10+F9 -> 354555.03 | G10: =F10+G9 -> 473111.04 | H10: =G10+H9 -> 615378.25 | I10: =H10+I9 -> 786098.9 | J10: =I10+J9 -> 990963.67 | ... M10: =L10+M9 -> 1885813
A12: Year 1 total revenue | B12: =SUM(B9:M9) -> 1885813

Sheet 3-Year Plan & Valuation
A1: 3-Year Plan & Path to ₹100 Crore
B2: Year 1 | C2: Year 2 | D2: Year 3
A3: Exit MAU (month 12/24/36) | B3: ='Year 1 Monthly'!M3 -> 37150.419 | C3: =B3*(1+Assumptions!$B$6)^12 -> 144737.14 | D3: =C3*(1+Assumptions!$B$7)^12 -> 364472.74
A4: Average MAU | B4: =(Assumptions!B4+B3)/2 -> 21075.209 | C4: =(B3+C3)/2 -> 90943.779 | D4: =(C3+D3)/2 -> 254604.94
A6: Subscription revenue | B6: =B4*12*Assumptions!$B$35 -> 1254396.5 | C6: =C4*12*Assumptions!$B$35 -> 5412973.7 | D6: =D4*12*Assumptions!$B$35 -> 15154086
A7: Occasion pack revenue | B7: =B4*12*Assumptions!$B$36 -> 815610.6 | C7: =C4*12*Assumptions!$B$36 -> 3519524.2 | D7: =D4*12*Assumptions!$B$36 -> 9853211.1
A8: Affiliate revenue | B8: =B4*12*Assumptions!$B$37 -> 339900.98 | C8: =C4*12*Assumptions!$B$37 -> 1466741.3 | D8: =D4*12*Assumptions!$B$37 -> 4106268.4
A9: Stylist marketplace revenue | B9: 0 | C9: =C4*12*Assumptions!$B$38 -> 490114.21 | D9: =D4*12*Assumptions!$B$38 -> 1372116.9
A10: Total annual revenue | B10: =SUM(B6:B9) -> 2409908 | C10: =SUM(C6:C9) -> 10889353 | D10: =SUM(D6:D9) -> 30485682
A12: Exit-month ARR (run-rate) | B12: =B3*12*Assumptions!$B$39 -> 4248076.1 | C12: =C3*12*Assumptions!$B$40 -> 17330420 | D12: =D3*12*Assumptions!$B$40 -> 43640945
A13: Implied valuation (ARR × multiple) | B13: =B12*Assumptions!$B$31 -> 29736532 | C13: =C12*Assumptions!$B$31 -> 1.2131294e+08 | D13: =D12*Assumptions!$B$31 -> 3.0548662e+08
A15: PATH TO ₹100 CRORE
A16: Required ARR at target multiple | B16: =Assumptions!B32/Assumptions!B31 -> 1.4285714e+08
A17: Required MAU (at current per-MAU revenue) | B17: =B16/12/Assumptions!B40 -> 1193089.1
A18: Levers if MAU falls short | B18: Raise conversion 3%→5%, add packs, grow affiliate AOV
